stringkernels/__init__.py
stringkernels/kernels.py
stringkernels/utils.py
string_kernels-1.1.2.dist-info/LICENSE
string_kernels-1.1.2.dist-info/METADATA
string_kernels-1.1.2.dist-info/WHEEL
string_kernels-1.1.2.dist-info/top_level.txt
string_kernels-1.1.2.dist-info/RECORD
