Metadata-Version: 2.1
Name: string-kernels
Version: 1.1.2
Summary: Polynomial String Kernel and linear time String Kernel. Supports multithreading and is compatible with Scikit-Learn SVMs.
Home-page: https://github.com/weekend37/string-kernels
Author: Helgi Hilmarsson
Author-email: helgi37@gmail.com
License: UNKNOWN
Project-URL: Bug Tracker, https://github.com/weekend37/string-kernels/issues
Platform: UNKNOWN
Classifier: Programming Language :: Python :: 3
Classifier: License :: OSI Approved :: Academic Free License (AFL)
Classifier: Operating System :: OS Independent
Requires-Python: >=3.6
License-File: LICENSE
